pycot/__init__.py
pycot/config.py
pycot/exceptions.py
pycot/reports.py
pycot/version.py
pycot/store/contract_names.json
pycot/store/cot_reports_data.json
pycot/store/format_columns.json
pycot_reports-0.1.2.dist-info/LICENSE
pycot_reports-0.1.2.dist-info/METADATA
pycot_reports-0.1.2.dist-info/WHEEL
pycot_reports-0.1.2.dist-info/top_level.txt
pycot_reports-0.1.2.dist-info/RECORD
