Metadata-Version: 2.1
Name: pycot-reports
Version: 0.1.2
Summary: Python Library for interacting with the CFTC Commitment of Traders reports.
Home-page: https://github.com/philsv/pycot
Author: philsv
Author-email: frphsv@gmail.com
License: MIT
Keywords: commitment of traders,cot data,cftc,python
Platform: UNKNOWN
Classifier: Development Status :: 2 - Pre-Alpha
Classifier: Intended Audience :: Developers
Classifier: Programming Language :: Python :: 3
Classifier: Programming Language :: Python :: 3.6
Classifier: Programming Language :: Python :: 3.7
Classifier: Programming Language :: Python :: 3.8
Classifier: Programming Language :: Python :: 3.9
Classifier: Programming Language :: Python :: 3.10
Classifier: Operating System :: Microsoft :: Windows
Classifier: Operating System :: Unix
Classifier: Operating System :: MacOS :: MacOS X
Classifier: License :: OSI Approved :: MIT License
Requires-Dist: pandas
Requires-Dist: requests
Requires-Dist: python-dotenv
